USEFS/__init__.py
examples/usefs_functions_example.py
examples/usefs_json.py
examples/usefs_toml.py
examples/usefs_yaml.py
USEFS_Python-0.2.1.dist-info/LICENSE
USEFS_Python-0.2.1.dist-info/METADATA
USEFS_Python-0.2.1.dist-info/WHEEL
USEFS_Python-0.2.1.dist-info/entry_points.txt
USEFS_Python-0.2.1.dist-info/top_level.txt
USEFS_Python-0.2.1.dist-info/RECORD
