Metadata-Version: 2.2
Name: USEFS_Python
Version: 0.2.1
Summary: USEFS access framework for Python
Author-email: SRInternet <srinternet@qq.com>
License: MIT License
Project-URL: homepage, https://github.com/SRON-org/USEFS_Python
Project-URL: repository, https://github.com/SRON-org/USEFS_Python
Classifier: Programming Language :: Python :: 3
Classifier: License :: OSI Approved :: MIT License
Classifier: Operating System :: OS Independent
Requires-Python: >=3.7
License-File: LICENSE
Requires-Dist: pyyaml
Requires-Dist: toml
Provides-Extra: dev
Requires-Dist: pytest; extra == "dev"
